{
  "_id": 240,
  "name": "HRtoCVR",
  "modversion": "0.1.20",
  "gameversion": "2025r179",
  "loaderversion": "v0.7.0",
  "modtype": "Mod",
  "author": "NovaVoidHowl",
  "description": "This mod provides Heart Rate values as avatar animator parameters, please see source link for more information.",
  "searchtags": [
    "animator",
    "parameter",
    "heart rate"
  ],
  "requirements": [],
  "downloadlink": "https://github.com/NovaVoidHowl/CVR_Mods/releases/download/r6/HRtoCVR.dll",
  "sourcelink": "https://github.com/NovaVoidHowl/CVR_Mods/tree/main/HRtoCVR",
  "changelog": "Recompiled for 2025r180",
  "embedcolor": "FFBC00"
}
